MANIFEST.in
README.md
requirements-dev.txt
requirements.txt
setup.py
altunityrunner/__init__.py
altunityrunner/__version__.py
altunityrunner/_websocket.py
altunityrunner/altUnityObject.py
altunityrunner/alt_unity_key_code.py
altunityrunner/alt_unity_port_forwarding.py
altunityrunner/by.py
altunityrunner/exceptions.py
altunityrunner/logging.py
altunityrunner/player_pref_key_type.py
altunityrunner/runner.py
altunityrunner.egg-info/PKG-INFO
altunityrunner.egg-info/SOURCES.txt
altunityrunner.egg-info/dependency_links.txt
altunityrunner.egg-info/not-zip-safe
altunityrunner.egg-info/requires.txt
altunityrunner.egg-info/top_level.txt
altunityrunner/commands/__init__.py
altunityrunner/commands/base_command.py
altunityrunner/commands/get_png_screenshot.py
altunityrunner/commands/get_server_version.py
altunityrunner/commands/get_static_property.py
altunityrunner/commands/AltUnityTesterCommands/__init__.py
altunityrunner/commands/AltUnityTesterCommands/add_notification_listener.py
altunityrunner/commands/AltUnityTesterCommands/remove_notification_listener.py
altunityrunner/commands/AltUnityTesterCommands/set_server_logging.py
altunityrunner/commands/FindObjects/__init__.py
altunityrunner/commands/FindObjects/find_object.py
altunityrunner/commands/FindObjects/find_object_at_coordinates.py
altunityrunner/commands/FindObjects/find_object_which_contains.py
altunityrunner/commands/FindObjects/find_objects.py
altunityrunner/commands/FindObjects/find_objects_which_contains.py
altunityrunner/commands/FindObjects/wait_for_object.py
altunityrunner/commands/FindObjects/wait_for_object_to_not_be_present.py
altunityrunner/commands/FindObjects/wait_for_object_which_contains.py
altunityrunner/commands/InputActions/__init__.py
altunityrunner/commands/InputActions/begin_touch.py
altunityrunner/commands/InputActions/click_coordinates.py
altunityrunner/commands/InputActions/end_touch.py
altunityrunner/commands/InputActions/key_down.py
altunityrunner/commands/InputActions/key_up.py
altunityrunner/commands/InputActions/keys_down.py
altunityrunner/commands/InputActions/keys_up.py
altunityrunner/commands/InputActions/move_mouse.py
altunityrunner/commands/InputActions/move_touch.py
