Metadata-Version: 2.1
Name: altunityrunner
Version: 1.7.2
Summary: Python bindings for the AltUnity Tester framework. AltUnity Tester is an open-source UI driven test automation tool that helps you find objects in your game and interacts with them.
Home-page: https://gitlab.com/altom/altunity/altunitytester
Author: Altom Consulting
Author-email: altunitytester@altom.fi
License: GNU GPLv3
Project-URL: Bug Tracker, https://gitlab.com/altom/altunity/altunitytester/-/issues
Project-URL: Documentation, https://altom.com/altunity/docs/altunitytester/
Project-URL: Source, https://gitlab.com/altom/altunity/altunitytester
Keywords: unity testing tests
Platform: UNKNOWN
Classifier: Development Status :: 5 - Production/Stable
Classifier: Intended Audience :: Developers
Classifier: Intended Audience :: Other Audience
Classifier: License :: OSI Approved :: GNU General Public License v3 (GPLv3)
Classifier: Programming Language :: C#
Classifier: Programming Language :: Java
Classifier: Programming Language :: Cython
Classifier: Programming Language :: Python :: Implementation
Classifier: Programming Language :: Python :: Implementation :: CPython
Classifier: Programming Language :: Python :: 3 :: Only
Classifier: Programming Language :: Python :: 3.4
Classifier: Programming Language :: Python :: 3.5
Classifier: Programming Language :: Python :: 3.6
Classifier: Programming Language :: Python :: 3.7
Classifier: Programming Language :: Python :: 3.8
Classifier: Programming Language :: Python :: 3.9
Classifier: Operating System :: OS Independent
Classifier: Topic :: Games/Entertainment
Classifier: Topic :: Software Development :: Libraries
Classifier: Topic :: Software Development :: Testing
Classifier: Topic :: Software Development :: Testing :: Acceptance
Classifier: Topic :: Software Development :: Testing :: Unit
Requires-Python: >=3.4.0
